serverlessrepo/__init__.py
serverlessrepo/__version__.py
serverlessrepo/application_metadata.py
serverlessrepo/application_policy.py
serverlessrepo/exceptions.py
serverlessrepo/parser.py
serverlessrepo/permission_helper.py
serverlessrepo/publish.py
tests/unit/__init__.py
tests/unit/conftest.py
tests/unit/test_application_metadata.py
tests/unit/test_application_policy.py
tests/unit/test_parser.py
tests/unit/test_permission_helper.py
tests/unit/test_publish.py
serverlessrepo-0.1.9.dist-info/LICENSE
serverlessrepo-0.1.9.dist-info/METADATA
serverlessrepo-0.1.9.dist-info/WHEEL
serverlessrepo-0.1.9.dist-info/top_level.txt
serverlessrepo-0.1.9.dist-info/RECORD
