Metadata-Version: 2.1
Name: serverlessrepo
Version: 0.1.9
Summary: A Python library with convenience helpers for working with the AWS Serverless Application Repository.
Home-page: https://github.com/awslabs/aws-serverlessrepo-python
Author: Amazon Web Services
Author-email: aws-sam-developer@amazon.com
License: Apache 2.0
Keywords: AWS Serverless Application Repository
Platform: UNKNOWN
Classifier: Development Status :: 4 - Beta
Classifier: Environment :: Console
Classifier: Environment :: Other Environment
Classifier: Intended Audience :: Developers
Classifier: Intended Audience :: Information Technology
Classifier: License :: OSI Approved :: Apache Software License
Classifier: Operating System :: OS Independent
Classifier: Programming Language :: Python
Classifier: Programming Language :: Python :: 2.7
Classifier: Programming Language :: Python :: 3.4
Classifier: Programming Language :: Python :: 3.5
Classifier: Programming Language :: Python :: 3.6
Classifier: Programming Language :: Python :: 3.7
Classifier: Topic :: Internet
Classifier: Topic :: Software Development :: Build Tools
Classifier: Topic :: Utilities
Requires-Python: >=2.7, !=3.0.*, !=3.1.*, !=3.2.*, !=3.3.*
